itkwasm_image_io/__init__.py
itkwasm_image_io/_version.py
itkwasm_image_io/bio_rad_read_image.py
itkwasm_image_io/bio_rad_read_image_async.py
itkwasm_image_io/bio_rad_write_image.py
itkwasm_image_io/bio_rad_write_image_async.py
itkwasm_image_io/bmp_read_image.py
itkwasm_image_io/bmp_read_image_async.py
itkwasm_image_io/bmp_write_image.py
itkwasm_image_io/bmp_write_image_async.py
itkwasm_image_io/fdf_read_image.py
itkwasm_image_io/fdf_read_image_async.py
itkwasm_image_io/fdf_write_image.py
itkwasm_image_io/fdf_write_image_async.py
itkwasm_image_io/gdcm_read_image.py
itkwasm_image_io/gdcm_read_image_async.py
itkwasm_image_io/gdcm_write_image.py
itkwasm_image_io/gdcm_write_image_async.py
itkwasm_image_io/ge4_read_image.py
itkwasm_image_io/ge4_read_image_async.py
itkwasm_image_io/ge4_write_image.py
itkwasm_image_io/ge4_write_image_async.py
itkwasm_image_io/ge5_read_image.py
itkwasm_image_io/ge5_read_image_async.py
itkwasm_image_io/ge5_write_image.py
itkwasm_image_io/ge5_write_image_async.py
itkwasm_image_io/ge_adw_read_image.py
itkwasm_image_io/ge_adw_read_image_async.py
itkwasm_image_io/ge_adw_write_image.py
itkwasm_image_io/ge_adw_write_image_async.py
itkwasm_image_io/gipl_read_image.py
itkwasm_image_io/gipl_read_image_async.py
itkwasm_image_io/gipl_write_image.py
itkwasm_image_io/gipl_write_image_async.py
itkwasm_image_io/jpeg_read_image.py
itkwasm_image_io/jpeg_read_image_async.py
itkwasm_image_io/jpeg_write_image.py
itkwasm_image_io/jpeg_write_image_async.py
itkwasm_image_io/lsm_read_image.py
itkwasm_image_io/lsm_read_image_async.py
itkwasm_image_io/lsm_write_image.py
itkwasm_image_io/lsm_write_image_async.py
itkwasm_image_io/meta_read_image.py
itkwasm_image_io/meta_read_image_async.py
itkwasm_image_io/meta_write_image.py
itkwasm_image_io/meta_write_image_async.py
itkwasm_image_io/mgh_read_image.py
itkwasm_image_io/mgh_read_image_async.py
itkwasm_image_io/mgh_write_image.py
itkwasm_image_io/mgh_write_image_async.py
itkwasm_image_io/mrc_read_image.py
itkwasm_image_io-1.6.0.dist-info/METADATA
itkwasm_image_io-1.6.0.dist-info/WHEEL
itkwasm_image_io-1.6.0.dist-info/RECORD
